gdown/__init__.py
gdown/_indent.py
gdown/cached_download.py
gdown/cli.py
gdown/download.py
gdown/download_folder.py
gdown/exceptions.py
gdown/extractall.py
gdown/parse_url.py
gdown-5.0.1.dist-info/METADATA
gdown-5.0.1.dist-info/WHEEL
gdown-5.0.1.dist-info/entry_points.txt
gdown-5.0.1.dist-info/licenses/LICENSE
gdown-5.0.1.dist-info/RECORD
