Metadata-Version: 2.1
Name: gdown
Version: 5.0.1
Summary: Google Drive Public File/Folder Downloader
Project-URL: Homepage, https://github.com/wkentaro/gdown
Author-email: Kentaro Wada <www.kentaro.wada@gmail.com>
License: MIT
License-File: LICENSE
Keywords: curl,download,google-drive,wget
Classifier: Development Status :: 5 - Production/Stable
Classifier: Environment :: Console
Classifier: Intended Audience :: Developers
Classifier: License :: OSI Approved :: MIT License
Classifier: Operating System :: OS Independent
Classifier: Programming Language :: Python
Classifier: Programming Language :: Python :: 3 :: Only
Classifier: Programming Language :: Python :: 3.8
Classifier: Programming Language :: Python :: 3.9
Classifier: Programming Language :: Python :: 3.10
Classifier: Programming Language :: Python :: 3.11
Classifier: Programming Language :: Python :: 3.12
Classifier: Topic :: Software Development :: Libraries :: Python Modules
Requires-Python: >=3.8
Requires-Dist: beautifulsoup4
Requires-Dist: filelock
Requires-Dist: requests[socks]
Requires-Dist: tqdm
Provides-Extra: test
Requires-Dist: build; extra == 'test'
Requires-Dist: mypy; extra == 'test'
Requires-Dist: pytest; extra == 'test'
Requires-Dist: ruff; extra == 'test'
Requires-Dist: twine; extra == 'test'
Requires-Dist: types-requests; extra == 'test'
